subtitle_parser.py
subtitle_parser-2.0.1.dist-info/LICENSE
subtitle_parser-2.0.1.dist-info/METADATA
subtitle_parser-2.0.1.dist-info/WHEEL
subtitle_parser-2.0.1.dist-info/RECORD
